hip_vector_store/__init__.py
hip_vector_store/growlithe/client.py
hip_vector_store/growlithe/common/__init__.py
hip_vector_store/growlithe/core/__init__.py
hip_vector_store/growlithe/core/config.py
hip_vector_store/growlithe/registry/__init__.py
hip_vector_store/growlithe/registry/_growlithe_registry_client.py
hip_vector_store/growlithe/vector_store/_growlithe_vector_store_client.py
hip_vector_store-0.1.15.dist-info/METADATA
hip_vector_store-0.1.15.dist-info/WHEEL
hip_vector_store-0.1.15.dist-info/RECORD
